fake_winreg/__init__.py
fake_winreg/__init__conf__.py
fake_winreg/fake_reg.py
fake_winreg/fake_reg_tools.py
fake_winreg/fake_winreg.py
fake_winreg/fake_winreg_cli.py
fake_winreg/helpers.py
fake_winreg/py.typed
fake_winreg/registry_constants.py
fake_winreg/types_custom.py
fake_winreg-1.6.3.dist-info/LICENSE
fake_winreg-1.6.3.dist-info/METADATA
fake_winreg-1.6.3.dist-info/WHEEL
fake_winreg-1.6.3.dist-info/entry_points.txt
fake_winreg-1.6.3.dist-info/top_level.txt
fake_winreg-1.6.3.dist-info/RECORD
