Metadata-Version: 2.1
Name: fake-winreg
Version: 1.6.3
Summary: fake winreg, in order to test registry related functions on linux
Author-email: Robert Nowotny <bitranox@gmail.com>
License: MIT
Project-URL: Homepage, https://github.com/bitranox/fake_winreg
Project-URL: Documentation, https://github.com/bitranox/fake_winreg/blob/master/README.rst
Project-URL: Repository, https://github.com/bitranox/fake_winreg.git
Project-URL: Changelog, https://github.com/bitranox/fake_winreg/blob/master/CHANGES.rst
Classifier: Development Status :: 5 - Production/Stable
Classifier: Intended Audience :: Developers
Classifier: License :: OSI Approved :: MIT License
Classifier: Natural Language :: English
Classifier: Operating System :: OS Independent
Classifier: Programming Language :: Python
Classifier: Topic :: Software Development :: Libraries :: Python Modules
Requires-Python: >=3.8.0
Provides-Extra: test
License-File: LICENSE
